[{"url":"https://api.github.com/repos/owncloud/core/issues/comments/15908901","html_url":"https://github.com/owncloud/core/issues/2729#issuecomment-15908901","issue_url":"https://api.github.com/repos/owncloud/core/issues/2729","id":15908901,"user":{"login":"jpaechnatz","id":2646767,"avatar_url":"https://gravatar.com/avatar/aac43c081c5d914d989e1b2727e74008?d=https%3a%2f%2fidenticons.github.com%2f112ef05882d35a8a556a75c30fcea042.png&r=x","gravatar_id":"aac43c081c5d914d989e1b2727e74008","url":"https://api.github.com/users/jpaechnatz","html_url":"https://github.com/jpaechnatz","followers_url":"https://api.github.com/users/jpaechnatz/followers","following_url":"https://api.github.com/users/jpaechnatz/following{/other_user}","gists_url":"https://api.github.com/users/jpaechnatz/gists{/gist_id}","starred_url":"https://api.github.com/users/jpaechnatz/starred{/owner}{/repo}","subscriptions_url":"https://api.github.com/users/jpaechnatz/subscriptions","organizations_url":"https://api.github.com/users/jpaechnatz/orgs","repos_url":"https://api.github.com/users/jpaechnatz/repos","events_url":"https://api.github.com/users/jpaechnatz/events{/privacy}","received_events_url":"https://api.github.com/users/jpaechnatz/received_events","type":"user","site_admin":false},"created_at":"2013-04-04t16:42:43z","updated_at":"2013-04-04t16:42:43z","body":"duplicate of https://github.com/owncloud/apps/issues/819 and closed since 15 days. why is it missing in 5.0.3 ???"},{"url":"https://api.github.com/repos/owncloud/core/issues/comments/16079421","html_url":"https://github.com/owncloud/core/issues/2729#issuecomment-16079421","issue_url":"https://api.github.com/repos/owncloud/core/issues/2729","id":16079421,"user":{"login":"deepdiver1975","id":1005065,"avatar_url":"https://gravatar.com/avatar/bdba071ed68da9ce8edae53c364902ef?d=https%3a%2f%2fidenticons.github.com%2f67e101ad9531b7d25697b76e503e062e.png&r=x","gravatar_id":"bdba071ed68da9ce8edae53c364902ef","url":"https://api.github.com/users/deepdiver1975","html_url":"https://github.com/deepdiver1975","followers_url":"https://api.github.com/users/deepdiver1975/followers","following_url":"https://api.github.com/users/deepdiver1975/following{/other_user}","gists_url":"https://api.github.com/users/deepdiver1975/gists{/gist_id}","starred_url":"https://api.github.com/users/deepdiver1975/starred{/owner}{/repo}","subscriptions_url":"https://api.github.com/users/deepdiver1975/subscriptions","organizations_url":"https://api.github.com/users/deepdiver1975/orgs","repos_url":"https://api.github.com/users/deepdiver1975/repos","events_url":"https://api.github.com/users/deepdiver1975/events{/privacy}","received_events_url":"https://api.github.com/users/deepdiver1975/received_events","type":"user","site_admin":false},"created_at":"2013-04-08t21:18:55z","updated_at":"2013-04-08t21:18:55z","body":"we need this issue in the apps repo - thx"}]