[{"url":"https://api.github.com/repos/owncloud/core/issues/comments/23992668","html_url":"https://github.com/owncloud/core/issues/4456#issuecomment-23992668","issue_url":"https://api.github.com/repos/owncloud/core/issues/4456","id":23992668,"user":{"login":"kondou-ger","id":1410802,"avatar_url":"https://gravatar.com/avatar/917dab919ae812f8252b2f501c514b19?d=https%3a%2f%2fidenticons.github.com%2fd07869ed62cb1b7f88b731956ab913ee.png&r=x","gravatar_id":"917dab919ae812f8252b2f501c514b19","url":"https://api.github.com/users/kondou-ger","html_url":"https://github.com/kondou-ger","followers_url":"https://api.github.com/users/kondou-ger/followers","following_url":"https://api.github.com/users/kondou-ger/following{/other_user}","gists_url":"https://api.github.com/users/kondou-ger/gists{/gist_id}","starred_url":"https://api.github.com/users/kondou-ger/starred{/owner}{/repo}","subscriptions_url":"https://api.github.com/users/kondou-ger/subscriptions","organizations_url":"https://api.github.com/users/kondou-ger/orgs","repos_url":"https://api.github.com/users/kondou-ger/repos","events_url":"https://api.github.com/users/kondou-ger/events{/privacy}","received_events_url":"https://api.github.com/users/kondou-ger/received_events","type":"user","site_admin":false},"created_at":"2013-09-07t11:28:26z","updated_at":"2013-09-07t11:28:26z","body":"#2721 \r\n>i never closed the issue.\r\n\r\n![screenshot417](https://f.cloud.github.com/assets/1410802/1101190/54e5f5c8-17b0-11e3-8b74-39a84065c797.png)\r\nyou closed it, and you're free to reopen it.\r\n\r\ncan you provide some php logs and data from owncloud.log?\r\n\r\n@icewind1991 "}]