{"url":"https://api.github.com/repos/owncloud/core/issues/2095","labels_url":"https://api.github.com/repos/owncloud/core/issues/2095/labels{/name}","comments_url":"https://api.github.com/repos/owncloud/core/issues/2095/comments","events_url":"https://api.github.com/repos/owncloud/core/issues/2095/events","html_url":"https://github.com/owncloud/core/issues/2095","id":11640370,"number":2095,"title":"5.0.0rc1 mar 4 build: deleted files doesn't list any of the deleted files or folders","user":{"login":"mtrichards","id":1818977,"avatar_url":"https://gravatar.com/avatar/a1655fd2e819638708ee854fa941008b?d=https%3a%2f%2fidenticons.github.com%2fa75d8baded229745ad65d43f7a7975df.png&r=x","gravatar_id":"a1655fd2e819638708ee854fa941008b","url":"https://api.github.com/users/mtrichards","html_url":"https://github.com/mtrichards","followers_url":"https://api.github.com/users/mtrichards/followers","following_url":"https://api.github.com/users/mtrichards/following{/other_user}","gists_url":"https://api.github.com/users/mtrichards/gists{/gist_id}","starred_url":"https://api.github.com/users/mtrichards/starred{/owner}{/repo}","subscriptions_url":"https://api.github.com/users/mtrichards/subscriptions","organizations_url":"https://api.github.com/users/mtrichards/orgs","repos_url":"https://api.github.com/users/mtrichards/repos","events_url":"https://api.github.com/users/mtrichards/events{/privacy}","received_events_url":"https://api.github.com/users/mtrichards/received_events","type":"user","site_admin":false},"labels":[{"url":"https://api.github.com/repos/owncloud/core/labels/attention","name":"attention","color":"d7e102"},{"url":"https://api.github.com/repos/owncloud/core/labels/bug","name":"bug","color":"fc2929"}],"state":"closed","assignee":null,"milestone":null,"comments":6,"created_at":"2013-03-04t21:40:23z","updated_at":"2013-08-07t18:29:21z","closed_at":"2013-08-07t18:29:21z","pull_request":{"html_url":null,"diff_url":null,"patch_url":null},"body":"i tried deleted files on windows, and while the files and folders delete, the deleted files or folders app don't show in the deleted files tab\r\n\r\ni log into owncloud\r\ni upload a few files in the web interface\r\ni delete a couple files\r\ni click on deleted files\r\nthere is nothing in the deleted files tab\r\n\r\nrunning on\r\nsql server 2008 r2\r\nwindows 2008 r2, iis\r\n\r\nlogs:\r\nwarning php undefined index: dirlisting at c:\\inetpub\\wwwroot\\owncloud\\apps\\files_trashbin\\templates\\index.php#8 march 4, 2013 16:06\r\nwarning php copy(c:/ownclouddata/admin/files-versions\\clientsync\\potato\\aeao\\img-2350-copy-6-jpg-v1362430528): failed to open stream: no such file or directory at c:\\inetpub\\wwwroot\\owncloud\\lib\\files\\storage\\mappedlocal.php#166 march 4, 2013 15:55\r\nwarning php invalid argument supplied for foreach() at c:\\inetpub\\wwwroot\\owncloud\\apps\\files_versions\\lib\\versions.php#397 march 4, 2013 15:55\r\nwarning php undefined index: all at c:\\inetpub\\wwwroot\\owncloud\\apps\\files_versions\\lib\\versions.php#387 march 4, 2013 15:55\r\nwarning php undefined index: by_file at c:\\inetpub\\wwwroot\\owncloud\\apps\\files_versions\\lib\\versions.php#386 march 4, 2013 15:55\r\nwarning php copy(c:/ownclouddata/admin/files-versions\\clientsync\\potato\\aeao\\img-2350-copy-4-jpg-v1362430516): failed to open stream: no such file or directory at c:\\inetpub\\wwwroot\\owncloud\\lib\\files\\storage\\mappedlocal.php#166 march 4, 2013 15:55\r\nwarning php copy(c:/ownclouddata/admin/files-versions\\clientsync\\potato\\aeao\\img-2350-copy-8-jpg-v1362430514): failed to open stream: no such file or directory at c:\\inetpub\\wwwroot\\owncloud\\lib\\files\\storage\\mappedlocal.php#166 march 4, 2013 15:55\r\nwarning php copy(c:/ownclouddata/admin/files-versions\\clientsync\\potato\\aeao\\img-2350-copy-7-jpg-v1362430513): failed to open stream: no such file or directory at c:\\inetpub\\wwwroot\\owncloud\\lib\\files\\storage\\mappedlocal.php#166 march 4, 2013 15:55\r\nwarning php copy(c:/ownclouddata/admin/files-versions\\clientsync\\potato\\aeao\\img-2350-copy-2-jpg-v1362430511): failed to open stream: no such file or directory at c:\\inetpub\\wwwroot\\owncloud\\lib\\files\\storage\\mappedlocal.php#166 march 4, 2013 15:55\r\nwarning php copy(c:/ownclouddata/admin/files-versions\\clientsync\\potato\\aeao\\img-2350-copy-5-jpg-v1362430508): failed to open stream: no such file or directory at c:\\inetpub\\wwwroot\\owncloud\\lib\\files\\storage\\mappedlocal.php#166 march 4, 2013 15:55\r\nwarning php copy(c:/ownclouddata/admin/files-versions\\clientsync\\potato\\aeao\\img-2350-copy-3-jpg-v1362430502): failed to open stream: no such file or directory at c:\\inetpub\\wwwroot\\owncloud\\lib\\files\\storage\\mappedlocal.php#166 march 4, 2013 15:55\r\nwarning php session_regenerate_id(): session object destruction failed at c:\\inetpub\\wwwroot\\owncloud\\lib\\user.php#253 march 4, 2013 15:52\r\nwarning php readdir() expects parameter 1 to be resource, boolean given at c:\\inetpub\\wwwroot\\owncloud\\lib\\cache\\fileglobal.php#91 march 4, 2013 15:45\r\nwarning php opendir(c:\\windows\\temp/owncloud-5135072bb2864/): failed to open dir: no such file or directory at c:\\inetpub\\wwwroot\\owncloud\\lib\\cache\\fileglobal.php#90 march 4, 2013 15:45\r\nwarning php opendir(c:\\windows\\temp/owncloud-5135072bb2864/,c:\\windows\\temp/owncloud-5135072bb2864/): access is denied. (code: 5) at c:\\inetpub\\wwwroot\\owncloud\\lib\\cache\\fileglobal.php#90 march 4, 2013 15:45\r\n\r\n\r\nwarning\tphp\tsession_start(): ps_files_cleanup_dir: opendir(c:\\windows\\temp) failed: no error (0) at c:\\inetpub\\wwwroot\\owncloud\\lib\\base.php#324\tmarch 4, 2013 16:35\r\nwarning\tphp\tundefined index: dirlisting at c:\\inetpub\\wwwroot\\owncloud\\apps\\files_trashbin\\templates\\index.php#8\tmarch 4, 2013 16:34\r\nwarning\tphp\ticonv(): detected an illegal character in input string at c:\\inetpub\\wwwroot\\owncloud\\lib\\files\\mapper.php#213\tmarch 4, 2013 16:23\r\nwarning\tphp\ticonv(): detected an illegal character in input string at c:\\inetpub\\wwwroot\\owncloud\\lib\\files\\mapper.php#213\tmarch 4, 2013 16:23\r\nwarning\tphp\ticonv(): detected an illegal character in input string at c:\\inetpub\\wwwroot\\owncloud\\lib\\files\\mapper.php#213\tmarch 4, 2013 16:23\r\nwarning\tphp\ticonv(): detected an illegal character in input string at c:\\inetpub\\wwwroot\\owncloud\\lib\\files\\mapper.php#213\tmarch 4, 2013 16:10\r\nwarning\tphp\tundefined index: dirlisting at c:\\inetpub\\wwwroot\\owncloud\\apps\\files_trashbin\\templates\\index.php#8\tmarch 4, 2013 16:06","closed_by":{"login":"jancborchardt","id":925062,"avatar_url":"https://gravatar.com/avatar/2fd3f4d5d762955e5b603794a888fa97?d=https%3a%2f%2fidenticons.github.com%2f84ec51f9ceed468217d4e13abf78da9c.png&r=x","gravatar_id":"2fd3f4d5d762955e5b603794a888fa97","url":"https://api.github.com/users/jancborchardt","html_url":"https://github.com/jancborchardt","followers_url":"https://api.github.com/users/jancborchardt/followers","following_url":"https://api.github.com/users/jancborchardt/following{/other_user}","gists_url":"https://api.github.com/users/jancborchardt/gists{/gist_id}","starred_url":"https://api.github.com/users/jancborchardt/starred{/owner}{/repo}","subscriptions_url":"https://api.github.com/users/jancborchardt/subscriptions","organizations_url":"https://api.github.com/users/jancborchardt/orgs","repos_url":"https://api.github.com/users/jancborchardt/repos","events_url":"https://api.github.com/users/jancborchardt/events{/privacy}","received_events_url":"https://api.github.com/users/jancborchardt/received_events","type":"user","site_admin":false}}