{"url":"https://api.github.com/repos/owncloud/core/issues/3313","labels_url":"https://api.github.com/repos/owncloud/core/issues/3313/labels{/name}","comments_url":"https://api.github.com/repos/owncloud/core/issues/3313/comments","events_url":"https://api.github.com/repos/owncloud/core/issues/3313/events","html_url":"https://github.com/owncloud/core/pull/3313","id":14234029,"number":3313,"title":"fixed problems with a dots in a filenames","user":{"login":"infoneo","id":4140590,"avatar_url":"https://gravatar.com/avatar/bc0a26326f8748680a48ed4ccc64a15b?d=https%3a%2f%2fidenticons.github.com%2ffbb06d5e5e769ae263f1c887fd5eadff.png&r=x","gravatar_id":"bc0a26326f8748680a48ed4ccc64a15b","url":"https://api.github.com/users/infoneo","html_url":"https://github.com/infoneo","followers_url":"https://api.github.com/users/infoneo/followers","following_url":"https://api.github.com/users/infoneo/following{/other_user}","gists_url":"https://api.github.com/users/infoneo/gists{/gist_id}","starred_url":"https://api.github.com/users/infoneo/starred{/owner}{/repo}","subscriptions_url":"https://api.github.com/users/infoneo/subscriptions","organizations_url":"https://api.github.com/users/infoneo/orgs","repos_url":"https://api.github.com/users/infoneo/repos","events_url":"https://api.github.com/users/infoneo/events{/privacy}","received_events_url":"https://api.github.com/users/infoneo/received_events","type":"user","site_admin":false},"labels":[],"state":"closed","assignee":null,"milestone":null,"comments":0,"created_at":"2013-05-12t12:12:49z","updated_at":"2013-05-12t13:29:33z","closed_at":"2013-05-12t12:18:16z","pull_request":{"html_url":"https://github.com/owncloud/core/pull/3313","diff_url":"https://github.com/owncloud/core/pull/3313.diff","patch_url":"https://github.com/owncloud/core/pull/3313.patch"},"body":"","closed_by":{"login":"infoneo","id":4140590,"avatar_url":"https://gravatar.com/avatar/bc0a26326f8748680a48ed4ccc64a15b?d=https%3a%2f%2fidenticons.github.com%2ffbb06d5e5e769ae263f1c887fd5eadff.png&r=x","gravatar_id":"bc0a26326f8748680a48ed4ccc64a15b","url":"https://api.github.com/users/infoneo","html_url":"https://github.com/infoneo","followers_url":"https://api.github.com/users/infoneo/followers","following_url":"https://api.github.com/users/infoneo/following{/other_user}","gists_url":"https://api.github.com/users/infoneo/gists{/gist_id}","starred_url":"https://api.github.com/users/infoneo/starred{/owner}{/repo}","subscriptions_url":"https://api.github.com/users/infoneo/subscriptions","organizations_url":"https://api.github.com/users/infoneo/orgs","repos_url":"https://api.github.com/users/infoneo/repos","events_url":"https://api.github.com/users/infoneo/events{/privacy}","received_events_url":"https://api.github.com/users/infoneo/received_events","type":"user","site_admin":false}}