{"url":"https://api.github.com/repos/owncloud/core/issues/6163","labels_url":"https://api.github.com/repos/owncloud/core/issues/6163/labels{/name}","comments_url":"https://api.github.com/repos/owncloud/core/issues/6163/comments","events_url":"https://api.github.com/repos/owncloud/core/issues/6163/events","html_url":"https://github.com/owncloud/core/issues/6163","id":23630546,"number":6163,"title":"owncloud6rc1 - shared doc is not editable","user":{"login":"hasafi","id":6093963,"avatar_url":"https://gravatar.com/avatar/9eeaba809c4b2ad3fefcfd3f90c32e32?d=https%3a%2f%2fidenticons.github.com%2f6238ad9348c9680615822e053e1a860a.png&r=x","gravatar_id":"9eeaba809c4b2ad3fefcfd3f90c32e32","url":"https://api.github.com/users/hasafi","html_url":"https://github.com/hasafi","followers_url":"https://api.github.com/users/hasafi/followers","following_url":"https://api.github.com/users/hasafi/following{/other_user}","gists_url":"https://api.github.com/users/hasafi/gists{/gist_id}","starred_url":"https://api.github.com/users/hasafi/starred{/owner}{/repo}","subscriptions_url":"https://api.github.com/users/hasafi/subscriptions","organizations_url":"https://api.github.com/users/hasafi/orgs","repos_url":"https://api.github.com/users/hasafi/repos","events_url":"https://api.github.com/users/hasafi/events{/privacy}","received_events_url":"https://api.github.com/users/hasafi/received_events","type":"user","site_admin":false},"labels":[],"state":"closed","assignee":null,"milestone":null,"comments":2,"created_at":"2013-12-03t09:33:27z","updated_at":"2013-12-03t10:08:47z","closed_at":"2013-12-03t10:08:47z","pull_request":{"html_url":null,"diff_url":null,"patch_url":null},"body":"owncloud6rc1 - shared doc is not editable","closed_by":{"login":"karlitschek","id":867445,"avatar_url":"https://gravatar.com/avatar/87ce2b4531ee1a0c32b50e0d8f049224?d=https%3a%2f%2fidenticons.github.com%2f06e7098636caebfc9c30c9f52eb905df.png&r=x","gravatar_id":"87ce2b4531ee1a0c32b50e0d8f049224","url":"https://api.github.com/users/karlitschek","html_url":"https://github.com/karlitschek","followers_url":"https://api.github.com/users/karlitschek/followers","following_url":"https://api.github.com/users/karlitschek/following{/other_user}","gists_url":"https://api.github.com/users/karlitschek/gists{/gist_id}","starred_url":"https://api.github.com/users/karlitschek/starred{/owner}{/repo}","subscriptions_url":"https://api.github.com/users/karlitschek/subscriptions","organizations_url":"https://api.github.com/users/karlitschek/orgs","repos_url":"https://api.github.com/users/karlitschek/repos","events_url":"https://api.github.com/users/karlitschek/events{/privacy}","received_events_url":"https://api.github.com/users/karlitschek/received_events","type":"user","site_admin":false}}