{"url":"https://api.github.com/repos/owncloud/core/issues/3423","labels_url":"https://api.github.com/repos/owncloud/core/issues/3423/labels{/name}","comments_url":"https://api.github.com/repos/owncloud/core/issues/3423/comments","events_url":"https://api.github.com/repos/owncloud/core/issues/3423/events","html_url":"https://github.com/owncloud/core/issues/3423","id":14495826,"number":3423,"title":"redirect to html logon page","user":{"login":"blind-coder","id":3063912,"avatar_url":"https://gravatar.com/avatar/75251d539d1026ad32f6ac7afa29fa19?d=https%3a%2f%2fidenticons.github.com%2f4c9c243280360cf8ca72f63a7da7a582.png&r=x","gravatar_id":"75251d539d1026ad32f6ac7afa29fa19","url":"https://api.github.com/users/blind-coder","html_url":"https://github.com/blind-coder","followers_url":"https://api.github.com/users/blind-coder/followers","following_url":"https://api.github.com/users/blind-coder/following{/other_user}","gists_url":"https://api.github.com/users/blind-coder/gists{/gist_id}","starred_url":"https://api.github.com/users/blind-coder/starred{/owner}{/repo}","subscriptions_url":"https://api.github.com/users/blind-coder/subscriptions","organizations_url":"https://api.github.com/users/blind-coder/orgs","repos_url":"https://api.github.com/users/blind-coder/repos","events_url":"https://api.github.com/users/blind-coder/events{/privacy}","received_events_url":"https://api.github.com/users/blind-coder/received_events","type":"user","site_admin":false},"labels":[{"url":"https://api.github.com/repos/owncloud/core/labels/bug","name":"bug","color":"fc2929"}],"state":"open","assignee":null,"milestone":null,"comments":13,"created_at":"2013-05-19t12:24:40z","updated_at":"2013-12-04t15:36:45z","closed_at":null,"pull_request":{"html_url":null,"diff_url":null,"patch_url":null},"body":"it seems that there's an irregularity when requesting pages without login credentials, see this issue in contacts: https://github.com/owncloud/contacts/issues/94\r\n\r\nshort version:\r\npropfind on /remote.php/carddav without login creds sends a cookie to the client.\r\npropfind on /remote.php/carddav with correct login creds and the cookie from the first request returns the html login page.\r\npropfind on /remote.php/carddav with correct login creds and without the cookie returns expected result.\r\n\r\nnote that this is most probably not a bug in the contacts app, but in a more basic functionality that got changed between 5.0.5 and 5.0.6.","closed_by":null}