{"url":"https://api.github.com/repos/owncloud/core/issues/6414","labels_url":"https://api.github.com/repos/owncloud/core/issues/6414/labels{/name}","comments_url":"https://api.github.com/repos/owncloud/core/issues/6414/comments","events_url":"https://api.github.com/repos/owncloud/core/issues/6414/events","html_url":"https://github.com/owncloud/core/issues/6414","id":24297364,"number":6414,"title":"owncloud causes mysql to use all disk resources.","user":{"login":"xjorgenx","id":3020272,"avatar_url":"https://gravatar.com/avatar/e4fa8433deba24485c999363481d6a4b?d=https%3a%2f%2fidenticons.github.com%2f94025d0ce5267f16204c40ac76cedec4.png&r=x","gravatar_id":"e4fa8433deba24485c999363481d6a4b","url":"https://api.github.com/users/xjorgenx","html_url":"https://github.com/xjorgenx","followers_url":"https://api.github.com/users/xjorgenx/followers","following_url":"https://api.github.com/users/xjorgenx/following{/other_user}","gists_url":"https://api.github.com/users/xjorgenx/gists{/gist_id}","starred_url":"https://api.github.com/users/xjorgenx/starred{/owner}{/repo}","subscriptions_url":"https://api.github.com/users/xjorgenx/subscriptions","organizations_url":"https://api.github.com/users/xjorgenx/orgs","repos_url":"https://api.github.com/users/xjorgenx/repos","events_url":"https://api.github.com/users/xjorgenx/events{/privacy}","received_events_url":"https://api.github.com/users/xjorgenx/received_events","type":"user","site_admin":false},"labels":[{"url":"https://api.github.com/repos/owncloud/core/labels/bug","name":"bug","color":"fc2929"},{"url":"https://api.github.com/repos/owncloud/core/labels/windows+server","name":"windows server","color":"0b02e1"}],"state":"open","assignee":null,"milestone":null,"comments":3,"created_at":"2013-12-14t18:57:58z","updated_at":"2013-12-17t04:23:19z","closed_at":null,"pull_request":{"html_url":null,"diff_url":null,"patch_url":null},"body":"owncloud is polling the database repetitively even when nothing is being done on the user side, causing the mysql database to consume full disk io. i am running on a windows server with apache as my web server.","closed_by":null}