{"url":"https://api.github.com/repos/owncloud/core/issues/2377","labels_url":"https://api.github.com/repos/owncloud/core/issues/2377/labels{/name}","comments_url":"https://api.github.com/repos/owncloud/core/issues/2377/comments","events_url":"https://api.github.com/repos/owncloud/core/issues/2377/events","html_url":"https://github.com/owncloud/core/issues/2377","id":12095531,"number":2377,"title":"problems with german \"umlaut\" in folder name","user":{"login":"mahnuh","id":978226,"avatar_url":"https://gravatar.com/avatar/c9c8ebe6a2dc4f789285e6777710e757?d=https%3a%2f%2fidenticons.github.com%2f6309981c73bf5d7b1a4f56b94649f4a3.png&r=x","gravatar_id":"c9c8ebe6a2dc4f789285e6777710e757","url":"https://api.github.com/users/mahnuh","html_url":"https://github.com/mahnuh","followers_url":"https://api.github.com/users/mahnuh/followers","following_url":"https://api.github.com/users/mahnuh/following{/other_user}","gists_url":"https://api.github.com/users/mahnuh/gists{/gist_id}","starred_url":"https://api.github.com/users/mahnuh/starred{/owner}{/repo}","subscriptions_url":"https://api.github.com/users/mahnuh/subscriptions","organizations_url":"https://api.github.com/users/mahnuh/orgs","repos_url":"https://api.github.com/users/mahnuh/repos","events_url":"https://api.github.com/users/mahnuh/events{/privacy}","received_events_url":"https://api.github.com/users/mahnuh/received_events","type":"user","site_admin":false},"labels":[{"url":"https://api.github.com/repos/owncloud/core/labels/bug","name":"bug","color":"fc2929"},{"url":"https://api.github.com/repos/owncloud/core/labels/needs+info","name":"needs info","color":"0b02e1"}],"state":"open","assignee":null,"milestone":null,"comments":31,"created_at":"2013-03-16t14:28:34z","updated_at":"2013-12-15t19:46:34z","closed_at":null,"pull_request":{"html_url":null,"diff_url":null,"patch_url":null},"body":"hi,\r\n\r\nif i create a folder with a german umlaut in the name, for example \"kontoauszã¼ge\", on my mac, the folder is of course instantly synchronised. then i open the webinterface, the folder appears twice, but on my mac there is still only one version of the folder.\r\nsee screenshot attached.\r\n![bildschirmfoto 2013-03-16 um 15 26 46](https://f.cloud.github.com/assets/978226/266932/ba5f1a96-8e45-11e2-9220-fdca908fb814.png)\r\n","closed_by":null}