{"url":"https://api.github.com/repos/owncloud/core/issues/4668","labels_url":"https://api.github.com/repos/owncloud/core/issues/4668/labels{/name}","comments_url":"https://api.github.com/repos/owncloud/core/issues/4668/comments","events_url":"https://api.github.com/repos/owncloud/core/issues/4668/events","html_url":"https://github.com/owncloud/core/issues/4668","id":18791703,"number":4668,"title":"feature request: alternate storage limits for external storage","user":{"login":"jeffclay","id":1380084,"avatar_url":"https://gravatar.com/avatar/d63a9464c973040375b51bb0d3c702df?d=https%3a%2f%2fidenticons.github.com%2f1d463c57861644c5feae0de3a4328e3b.png&r=x","gravatar_id":"d63a9464c973040375b51bb0d3c702df","url":"https://api.github.com/users/jeffclay","html_url":"https://github.com/jeffclay","followers_url":"https://api.github.com/users/jeffclay/followers","following_url":"https://api.github.com/users/jeffclay/following{/other_user}","gists_url":"https://api.github.com/users/jeffclay/gists{/gist_id}","starred_url":"https://api.github.com/users/jeffclay/starred{/owner}{/repo}","subscriptions_url":"https://api.github.com/users/jeffclay/subscriptions","organizations_url":"https://api.github.com/users/jeffclay/orgs","repos_url":"https://api.github.com/users/jeffclay/repos","events_url":"https://api.github.com/users/jeffclay/events{/privacy}","received_events_url":"https://api.github.com/users/jeffclay/received_events","type":"user","site_admin":false},"labels":[{"url":"https://api.github.com/repos/owncloud/core/labels/enhancement","name":"enhancement","color":"02e10c"}],"state":"open","assignee":null,"milestone":null,"comments":3,"created_at":"2013-08-30t14:48:04z","updated_at":"2013-11-29t12:08:53z","closed_at":null,"pull_request":{"html_url":null,"diff_url":null,"patch_url":null},"body":"currently, the users local storage restriction is applied to external storage paths/locations. it would be great to be able to either disable storage limits completely for external locations or to be able to set alternate storage restrictions per external storage location much in the same way local storage restrictions are handled.\r\n\r\nif i haven't made this very clear, please ask any questions and i will elaborate.\r\n\r\nthanks","closed_by":null}