{"url":"https://api.github.com/repos/owncloud/core/issues/213","labels_url":"https://api.github.com/repos/owncloud/core/issues/213/labels{/name}","comments_url":"https://api.github.com/repos/owncloud/core/issues/213/comments","events_url":"https://api.github.com/repos/owncloud/core/issues/213/events","html_url":"https://github.com/owncloud/core/issues/213","id":8057824,"number":213,"title":"admin panel takes 1 minute to load","user":{"login":"mtrichards","id":1818977,"avatar_url":"https://gravatar.com/avatar/a1655fd2e819638708ee854fa941008b?d=https%3a%2f%2fidenticons.github.com%2fa75d8baded229745ad65d43f7a7975df.png&r=x","gravatar_id":"a1655fd2e819638708ee854fa941008b","url":"https://api.github.com/users/mtrichards","html_url":"https://github.com/mtrichards","followers_url":"https://api.github.com/users/mtrichards/followers","following_url":"https://api.github.com/users/mtrichards/following{/other_user}","gists_url":"https://api.github.com/users/mtrichards/gists{/gist_id}","starred_url":"https://api.github.com/users/mtrichards/starred{/owner}{/repo}","subscriptions_url":"https://api.github.com/users/mtrichards/subscriptions","organizations_url":"https://api.github.com/users/mtrichards/orgs","repos_url":"https://api.github.com/users/mtrichards/repos","events_url":"https://api.github.com/users/mtrichards/events{/privacy}","received_events_url":"https://api.github.com/users/mtrichards/received_events","type":"user","site_admin":false},"labels":[{"url":"https://api.github.com/repos/owncloud/core/labels/bug","name":"bug","color":"fc2929"}],"state":"closed","assignee":null,"milestone":null,"comments":13,"created_at":"2012-11-02t12:52:20z","updated_at":"2013-12-13t12:19:44z","closed_at":"2012-11-16t10:38:03z","pull_request":{"html_url":null,"diff_url":null,"patch_url":null},"body":"the admin panel takes a long time to load and display, a full minute in this case.  freebsd 9 with zfs and mysql.  load up owncloud with a fresh install, or any install, click on the admin panel, and count the time.\r\n\r\napp server and db server are on the same server\r\nmysql 5.5.21\r\n\r\nmysql> select * from oc_appconfig;\r\n+-------------------+-----------------------------------+------------------------------+\r\n| appid             | configkey                         | configvalue                  |\r\n+-------------------+-----------------------------------+------------------------------+\r\n| core              | installedat                       | 1350037148.4445              |\r\n| core              | lastupdatedat                     | 1351159097.2961              |\r\n| admin_migrate     | installed_version                 | 0.1                          |\r\n| admin_migrate     | enabled                           | yes                          |\r\n| files_pdfviewer   | installed_version                 | 0.1                          |\r\n| files_pdfviewer   | enabled                           | yes                          |\r\n| files_sharing     | installed_version                 | 0.3.3                        |\r\n| core              | public_files                      | files_sharing/public.php     |\r\n| core              | public_webdav                     | files_sharing/public.php     |\r\n| files_sharing     | types                             | filesystem                   |\r\n| files_sharing     | enabled                           | yes                          |\r\n| user_migrate      | installed_version                 | 0.1                          |\r\n| user_migrate      | enabled                           | yes                          |\r\n| files_versions    | installed_version                 | 1.0.2                        |\r\n| files_versions    | types                             | filesystem                   |\r\n| files_versions    | enabled                           | no                           |\r\n| gallery           | installed_version                 | 0.5.1                        |\r\n| core              | public_gallery                    | gallery/sharing.php          |\r\n| gallery           | enabled                           | yes                          |\r\n| files             | installed_version                 | 1.1.6                        |\r\n| core              | remote_files                      | files/appinfo/remote.php     |\r\n| core              | remote_webdav                     | files/appinfo/remote.php     |\r\n| core              | remote_filesync                   | files/appinfo/filesync.php   |\r\n| files             | types                             | filesystem                   |\r\n| files             | enabled                           | yes                          |\r\n| media             | installed_version                 | 0.4.3                        |\r\n| core              | remote_ampache                    | media/remote.php             |\r\n| media             | enabled                           | yes                          |\r\n| contacts          | installed_version                 | 0.2.4                        |\r\n| core              | remote_contacts                   | contacts/appinfo/remote.php  |\r\n| core              | remote_carddav                    | contacts/appinfo/remote.php  |\r\n| contacts          | enabled                           | yes                          |\r\n| files_odfviewer   | installed_version                 | 0.1                          |\r\n| files_odfviewer   | enabled                           | yes                          |\r\n| files_texteditor  | installed_version                 | 0.3                          |\r\n| files_texteditor  | enabled                           | yes                          |\r\n| calendar          | installed_version                 | 0.6.1                        |\r\n| core              | remote_calendar                   | calendar/appinfo/remote.php  |\r\n| core              | remote_caldav                     | calendar/appinfo/remote.php  |\r\n| core              | public_calendar                   | calendar/share.php           |\r\n| core              | public_caldav                     | calendar/share.php           |\r\n| calendar          | enabled                           | yes                          |\r\n| files_imageviewer | installed_version                 | 1.0                          |\r\n| files_imageviewer | enabled                           | yes                          |\r\n| core              | remote_core.css                   | /core/minimizer.php          |\r\n| core              | remote_core.js                    | /core/minimizer.php          |\r\n| core              | backgroundjobs_task               | oc_cache_fileglobal-gc       |\r\n| core              | global_cache_gc_lastrun           | 1351159086                   |\r\n| core              | backgroundjobs_step               | queued_tasks                 |\r\n| user_ldap         | installed_version                 | 0.3.0.0                      |\r\n| user_ldap         | types                             | authentication               |\r\n| user_ldap         | enabled                           | yes                          |\r\n| user_ldap         | ldap_host                         | 10.0.38.10                   |\r\n| user_ldap         | ldap_port                         | 389                          |\r\n| user_ldap         | ldap_dn                           |                              |\r\n| user_ldap         | ldap_agent_password               |                              |\r\n| user_ldap         | ldap_base                         | ou=people,dc=databird,dc=com |\r\n| user_ldap         | ldap_base_users                   |                              |\r\n| user_ldap         | ldap_base_groups                  |                              |\r\n| user_ldap         | ldap_userlist_filter              | objectclass=posixaccount     |\r\n| user_ldap         | ldap_login_filter                 | uid=%uid                     |\r\n| user_ldap         | ldap_group_filter                 | objectclass=posixgroup       |\r\n| user_ldap         | ldap_display_name                 | uid                          |\r\n| user_ldap         | ldap_group_display_name           | cn                           |\r\n| user_ldap         | ldap_tls                          | 0                            |\r\n| user_ldap         | ldap_turn_off_cert_check          | 0                            |\r\n| user_ldap         | ldap_nocase                       | 0                            |\r\n| user_ldap         | ldap_quota_def                    |                              |\r\n| user_ldap         | ldap_quota_attr                   |                              |\r\n| user_ldap         | ldap_email_attr                   |                              |\r\n| user_ldap         | ldap_group_member_assoc_attribute | uniquemember                 |\r\n| user_ldap         | ldap_cache_ttl                    | 600                          |\r\n| user_ldap         | home_folder_naming_rule           | opt:username                 |\r\n| user_ldap         | bgjupdategroupslastrun            | 1351158211                   |\r\n| core              | backgroundjobs_mode               | ajax                         |\r\n| core              | backgroundjobs_pid                | 96271                        |\r\n+-------------------+-----------------------------------+------------------------------+\r\n\r\n+-----------------+-----------+-----------+-----------------------------------------------------------------+\r\n| userid          | appid     | configkey | configvalue                                                     |\r\n+-----------------+-----------+-----------+-----------------------------------------------------------------+\r\n| chris           | user_ldap | homedir   | /usr/www/owncloud.databird.com/public_html/data/chris           |\r\n| chris           | calendar  | timezone  | europe/brussels                                                 |\r\n| rubenvanderzwan | user_ldap | homedir   | /usr/www/owncloud.databird.com/public_html/data/rubenvanderzwan |\r\n| rubenvanderzwan | calendar  | timezone  | europe/brussels                                                 |\r\n| ovdleun         | user_ldap | homedir   | /usr/www/owncloud.databird.com/public_html/data/ovdleun         |\r\n| rdevos72        | user_ldap | homedir   | /usr/www/owncloud.databird.com/public_html/data/rdevos72        |\r\n| rdevos72        | settings  | email     | rdevos72@gmail.com                                              |\r\n| admin           | calendar  | timezone  | europe/brussels                                                 |\r\n| rubenvanderzwan | files     | quota     | 1000 gb                                                         |\r\n| rubenvanderzwan | login     | token     | c5225cdfb7a91ebe8694f8b652ad168a                                |\r\n| onlineopslag    | user_ldap | homedir   | /usr/www/owncloud.databird.com/public_html/data/onlineopslag    |\r\n+-----------------+-----------+-----------+-----------------------------------------------------------------+\r\n\r\n\r\nmysql> select count(*) from oc_fscache;\r\n+----------+\r\n| count(*) |\r\n+----------+\r\n|   169220 |\r\n+----------+\r\n1 row in set (0.05 sec)\r\n\r\n<?php\r\n$config = array (\r\n  'passwordsalt' => hidden',\r\n  'datadirectory' => '/databird/accounts',\r\n  'dbtype' => 'mysql',\r\n  'version' => '4.90.0',\r\n  'dbname' => 'owncloud',\r\n  'dbhost' => 'localhost',\r\n  'dbtableprefix' => 'oc_',\r\n  'dbuser' => 'owncloud',\r\n  'dbpassword' => 'hidden',\r\n  'installed' => true,\r\n  'instanceid' => '5077ee9f50d6c',\r\n  'ldapignorenamingrules' => false,\r\n  'loglevel' => '0',\r\n);\r\n","closed_by":{"login":"karlitschek","id":867445,"avatar_url":"https://gravatar.com/avatar/87ce2b4531ee1a0c32b50e0d8f049224?d=https%3a%2f%2fidenticons.github.com%2f06e7098636caebfc9c30c9f52eb905df.png&r=x","gravatar_id":"87ce2b4531ee1a0c32b50e0d8f049224","url":"https://api.github.com/users/karlitschek","html_url":"https://github.com/karlitschek","followers_url":"https://api.github.com/users/karlitschek/followers","following_url":"https://api.github.com/users/karlitschek/following{/other_user}","gists_url":"https://api.github.com/users/karlitschek/gists{/gist_id}","starred_url":"https://api.github.com/users/karlitschek/starred{/owner}{/repo}","subscriptions_url":"https://api.github.com/users/karlitschek/subscriptions","organizations_url":"https://api.github.com/users/karlitschek/orgs","repos_url":"https://api.github.com/users/karlitschek/repos","events_url":"https://api.github.com/users/karlitschek/events{/privacy}","received_events_url":"https://api.github.com/users/karlitschek/received_events","type":"user","site_admin":false}}